{
    "schemaVersion": 1,
    "id": "noenchantcap",
    "version": "${version}",
    "name": "No Enchant Cap",
    "description": "A simple mod to enhance some aspects of enchanting.",
    "authors": [
      "AmyMialee"
    ],
    "contact": {
      "homepage": "https://github.com/AmyMialeeMods/no-enchant-cap",
      "issues": "https://github.com/AmyMialeeMods/no-enchant-cap/issues",
      "sources": "https://github.com/AmyMialeeMods/no-enchant-cap"
    },
    "license": "All-Rights-Reserved",
    "icon": "assets/noenchantcap/icon.png",
    "environment": "*",
    "entrypoints": {
      "preLaunch": [
        "xyz.amymialee.noenchantcap.NoEnchantCapPreLaunch"
      ],
      "main": [
        "xyz.amymialee.noenchantcap.NoEnchantCapFabric"
      ]
    },
    "mixins": [
      "noenchantcap.fabric.mixins.json",
      "noenchantcap.common.mixins.json"
    ],
    "depends": {
      "fabric": "*"
    }
  }
  